{
"type": "FeatureCollection",
"name": "geo_20_短期入所療養介護（介護医療院）",
"crs": { "type": "name", "properties": { "name": "urn:ogc:def:crs:OGC:1.3:CRS84" } },
"features": [
{ "type": "Feature", "properties": { "緯度": 36.2394851, "経度": 137.9624723, "url": "https://www.kaigokensaku.mhlw.go.jp/20/index.php?action_kouhyou_detail_004_kani=true&JigyosyoCd=20B0200016-00&ServiceCd=551&Type=search", "url2": "http://www.shironishi.or.jp/sh/", "内容": "社会医療法人城西医療財団城西病院介護医療院【短期入所療養介護（介護医療院）】長野県松本市城西１丁目５番１６号", "サービスの種類": "短期入所療養介護（介護医療院）" }, "geometry": { "type": "Point", "coordinates": [ 137.9624723, 36.2394851 ] } },
{ "type": "Feature", "properties": { "緯度": 36.338161, "経度": 138.2703063, "url": "https://www.kaigokensaku.mhlw.go.jp/20/index.php?action_kouhyou_detail_004_kani=true&JigyosyoCd=20B0300014-00&ServiceCd=551&Type=search", "url2": "http://maruyamakai.or.jp/maruko-hp/", "内容": "丸子中央病院【短期入所療養介護（介護医療院）】長野県上田市中丸子1771番地1", "サービスの種類": "短期入所療養介護（介護医療院）" }, "geometry": { "type": "Point", "coordinates": [ 138.270306299999987, 36.338161 ] } },
{ "type": "Feature", "properties": { "緯度": 35.5169998, "経度": 137.821635, "url": "https://www.kaigokensaku.mhlw.go.jp/20/index.php?action_kouhyou_detail_004_kani=true&JigyosyoCd=20B0500019-00&ServiceCd=551&Type=search", "url2": "https://nishizawa-hp.jp/", "内容": "介護医療院　西澤病院【短期入所療養介護（介護医療院）】長野県飯田市本町４丁目５番地", "サービスの種類": "短期入所療養介護（介護医療院）" }, "geometry": { "type": "Point", "coordinates": [ 137.821635, 35.5169998 ] } },
{ "type": "Feature", "properties": { "緯度": 36.3262293, "経度": 138.4268434, "url": "https://www.kaigokensaku.mhlw.go.jp/20/index.php?action_kouhyou_detail_004_kani=true&JigyosyoCd=20B0800021-00&ServiceCd=551&Type=search", "url2": "http://komoro-hosp.jp/", "内容": "小諸病院介護医療院【短期入所療養介護（介護医療院）】長野県小諸市荒町2丁目1-1", "サービスの種類": "短期入所療養介護（介護医療院）" }, "geometry": { "type": "Point", "coordinates": [ 138.4268434, 36.3262293 ] } },
{ "type": "Feature", "properties": { "緯度": 36.1112491, "経度": 137.9324494, "url": "https://www.kaigokensaku.mhlw.go.jp/20/index.php?action_kouhyou_detail_004_kani=true&JigyosyoCd=20B1500018-00&ServiceCd=551&Type=search", "url2": "http：//www.keijinn-kai.jp/", "内容": "介護医療院　添え木【短期入所療養介護（介護医療院）】長野県塩尻市大字宗賀1295", "サービスの種類": "短期入所療養介護（介護医療院）" }, "geometry": { "type": "Point", "coordinates": [ 137.9324494, 36.1112491 ] } },
{ "type": "Feature", "properties": { "緯度": 35.6002061, "経度": 137.9108844, "url": "https://www.kaigokensaku.mhlw.go.jp/20/index.php?action_kouhyou_detail_004_kani=true&JigyosyoCd=20B2500033-00&ServiceCd=551&Type=search", "url2": "https://shimoina.jrc.or.jp", "内容": "下伊那赤十字病院介護医療院【短期入所療養介護（介護医療院）】長野県下伊那郡松川町元大島3159-1", "サービスの種類": "短期入所療養介護（介護医療院）" }, "geometry": { "type": "Point", "coordinates": [ 137.910884399999986, 35.6002061 ] } },
{ "type": "Feature", "properties": { "緯度": 35.5511657, "経度": 137.8886715, "url": "https://www.kaigokensaku.mhlw.go.jp/20/index.php?action_kouhyou_detail_004_kani=true&JigyosyoCd=20B2500017-00&ServiceCd=551&Type=search", "url2": "http://shimoina-hp.jp", "内容": "介護医療院【短期入所療養介護（介護医療院）】長野県下伊那郡高森町吉田481番地13", "サービスの種類": "短期入所療養介護（介護医療院）" }, "geometry": { "type": "Point", "coordinates": [ 137.888671499999987, 35.5511657 ] } },
{ "type": "Feature", "properties": { "緯度": 35.8347978, "経度": 137.6834008, "url": "https://www.kaigokensaku.mhlw.go.jp/20/index.php?action_kouhyou_detail_004_kani=true&JigyosyoCd=20B2600015-00&ServiceCd=551&Type=search", "url2": "https://kiso-hosp.jp/", "内容": "長野県立木曽病院介護医療院【短期入所療養介護（介護医療院）】長野県木曽郡木曽町福島6613－4", "サービスの種類": "短期入所療養介護（介護医療院）" }, "geometry": { "type": "Point", "coordinates": [ 137.683400799999987, 35.8347978 ] } }
]
}
